{
  "concurrency": 8,
  "deployment": "dsqwen-14b-nscc-ds-4a100-node9-gpu-2-3",
  "duration_s": 447.127,
  "gpu_uuid": "GPU-3a113474-dd92-6d52-d05b-491e7b020ded,GPU-3c2fb581-708a-5fef-3eaa-5c3cc21a028e",
  "gpu_uuids": [
    "GPU-3a113474-dd92-6d52-d05b-491e7b020ded",
    "GPU-3c2fb581-708a-5fef-3eaa-5c3cc21a028e"
  ],
  "model": "dsqwen-14b",
  "pod": {
    "ip": "10.244.3.67",
    "name": "dsqwen-14b-nscc-ds-4a100-node9-gpu-2-3-84f8576d97-xkjjq"
  },
  "requests_per_round": 200,
  "rounds": 10,
  "samples": [
    {
      "event": "ready",
      "gpu": {
        "gpus": {
          "GPU-3a113474-dd92-6d52-d05b-491e7b020ded": {
            "processes": 2,
            "used_mib": 2856
          },
          "GPU-3c2fb581-708a-5fef-3eaa-5c3cc21a028e": {
            "processes": 3,
            "used_mib": 3910
          }
        },
        "raw": {
          "GPU-3a113474-dd92-6d52-d05b-491e7b020ded": [
            {
              "pid": "3763514",
              "used_mib": 1090
            },
            {
              "pid": "3779038",
              "used_mib": 1766
            }
          ],
          "GPU-3c2fb581-708a-5fef-3eaa-5c3cc21a028e": [
            {
              "pid": "3641391",
              "used_mib": 1054
            },
            {
              "pid": "3649478",
              "used_mib": 1090
            },
            {
              "pid": "3779039",
              "used_mib": 1766
            }
          ]
        },
        "total_used_mib": 6766
      }
    },
    {
      "event": "round_0_wake",
      "gpu": {
        "gpus": {
          "GPU-3a113474-dd92-6d52-d05b-491e7b020ded": {
            "processes": 2,
            "used_mib": 38184
          },
          "GPU-3c2fb581-708a-5fef-3eaa-5c3cc21a028e": {
            "processes": 3,
            "used_mib": 39238
          }
        },
        "raw": {
          "GPU-3a113474-dd92-6d52-d05b-491e7b020ded": [
            {
              "pid": "3763514",
              "used_mib": 1090
            },
            {
              "pid": "3779038",
              "used_mib": 37094
            }
          ],
          "GPU-3c2fb581-708a-5fef-3eaa-5c3cc21a028e": [
            {
              "pid": "3641391",
              "used_mib": 1054
            },
            {
              "pid": "3649478",
              "used_mib": 1090
            },
            {
              "pid": "3779039",
              "used_mib": 37094
            }
          ]
        },
        "total_used_mib": 77422
      }
    },
    {
      "event": "round_0_sleep",
      "gpu": {
        "gpus": {
          "GPU-3a113474-dd92-6d52-d05b-491e7b020ded": {
            "processes": 2,
            "used_mib": 2856
          },
          "GPU-3c2fb581-708a-5fef-3eaa-5c3cc21a028e": {
            "processes": 3,
            "used_mib": 3910
          }
        },
        "raw": {
          "GPU-3a113474-dd92-6d52-d05b-491e7b020ded": [
            {
              "pid": "3763514",
              "used_mib": 1090
            },
            {
              "pid": "3779038",
              "used_mib": 1766
            }
          ],
          "GPU-3c2fb581-708a-5fef-3eaa-5c3cc21a028e": [
            {
              "pid": "3641391",
              "used_mib": 1054
            },
            {
              "pid": "3649478",
              "used_mib": 1090
            },
            {
              "pid": "3779039",
              "used_mib": 1766
            }
          ]
        },
        "total_used_mib": 6766
      }
    },
    {
      "event": "round_1_wake",
      "gpu": {
        "gpus": {
          "GPU-3a113474-dd92-6d52-d05b-491e7b020ded": {
            "processes": 2,
            "used_mib": 38184
          },
          "GPU-3c2fb581-708a-5fef-3eaa-5c3cc21a028e": {
            "processes": 3,
            "used_mib": 39238
          }
        },
        "raw": {
          "GPU-3a113474-dd92-6d52-d05b-491e7b020ded": [
            {
              "pid": "3763514",
              "used_mib": 1090
            },
            {
              "pid": "3779038",
              "used_mib": 37094
            }
          ],
          "GPU-3c2fb581-708a-5fef-3eaa-5c3cc21a028e": [
            {
              "pid": "3641391",
              "used_mib": 1054
            },
            {
              "pid": "3649478",
              "used_mib": 1090
            },
            {
              "pid": "3779039",
              "used_mib": 37094
            }
          ]
        },
        "total_used_mib": 77422
      }
    },
    {
      "event": "round_1_sleep",
      "gpu": {
        "gpus": {
          "GPU-3a113474-dd92-6d52-d05b-491e7b020ded": {
            "processes": 2,
            "used_mib": 2856
          },
          "GPU-3c2fb581-708a-5fef-3eaa-5c3cc21a028e": {
            "processes": 3,
            "used_mib": 3910
          }
        },
        "raw": {
          "GPU-3a113474-dd92-6d52-d05b-491e7b020ded": [
            {
              "pid": "3763514",
              "used_mib": 1090
            },
            {
              "pid": "3779038",
              "used_mib": 1766
            }
          ],
          "GPU-3c2fb581-708a-5fef-3eaa-5c3cc21a028e": [
            {
              "pid": "3641391",
              "used_mib": 1054
            },
            {
              "pid": "3649478",
              "used_mib": 1090
            },
            {
              "pid": "3779039",
              "used_mib": 1766
            }
          ]
        },
        "total_used_mib": 6766
      }
    },
    {
      "event": "round_2_wake",
      "gpu": {
        "gpus": {
          "GPU-3a113474-dd92-6d52-d05b-491e7b020ded": {
            "processes": 2,
            "used_mib": 38184
          },
          "GPU-3c2fb581-708a-5fef-3eaa-5c3cc21a028e": {
            "processes": 3,
            "used_mib": 39238
          }
        },
        "raw": {
          "GPU-3a113474-dd92-6d52-d05b-491e7b020ded": [
            {
              "pid": "3763514",
              "used_mib": 1090
            },
            {
              "pid": "3779038",
              "used_mib": 37094
            }
          ],
          "GPU-3c2fb581-708a-5fef-3eaa-5c3cc21a028e": [
            {
              "pid": "3641391",
              "used_mib": 1054
            },
            {
              "pid": "3649478",
              "used_mib": 1090
            },
            {
              "pid": "3779039",
              "used_mib": 37094
            }
          ]
        },
        "total_used_mib": 77422
      }
    },
    {
      "event": "round_2_sleep",
      "gpu": {
        "gpus": {
          "GPU-3a113474-dd92-6d52-d05b-491e7b020ded": {
            "processes": 2,
            "used_mib": 2856
          },
          "GPU-3c2fb581-708a-5fef-3eaa-5c3cc21a028e": {
            "processes": 3,
            "used_mib": 3910
          }
        },
        "raw": {
          "GPU-3a113474-dd92-6d52-d05b-491e7b020ded": [
            {
              "pid": "3763514",
              "used_mib": 1090
            },
            {
              "pid": "3779038",
              "used_mib": 1766
            }
          ],
          "GPU-3c2fb581-708a-5fef-3eaa-5c3cc21a028e": [
            {
              "pid": "3641391",
              "used_mib": 1054
            },
            {
              "pid": "3649478",
              "used_mib": 1090
            },
            {
              "pid": "3779039",
              "used_mib": 1766
            }
          ]
        },
        "total_used_mib": 6766
      }
    },
    {
      "event": "round_3_wake",
      "gpu": {
        "gpus": {
          "GPU-3a113474-dd92-6d52-d05b-491e7b020ded": {
            "processes": 2,
            "used_mib": 38184
          },
          "GPU-3c2fb581-708a-5fef-3eaa-5c3cc21a028e": {
            "processes": 3,
            "used_mib": 39238
          }
        },
        "raw": {
          "GPU-3a113474-dd92-6d52-d05b-491e7b020ded": [
            {
              "pid": "3763514",
              "used_mib": 1090
            },
            {
              "pid": "3779038",
              "used_mib": 37094
            }
          ],
          "GPU-3c2fb581-708a-5fef-3eaa-5c3cc21a028e": [
            {
              "pid": "3641391",
              "used_mib": 1054
            },
            {
              "pid": "3649478",
              "used_mib": 1090
            },
            {
              "pid": "3779039",
              "used_mib": 37094
            }
          ]
        },
        "total_used_mib": 77422
      }
    },
    {
      "event": "round_3_sleep",
      "gpu": {
        "gpus": {
          "GPU-3a113474-dd92-6d52-d05b-491e7b020ded": {
            "processes": 2,
            "used_mib": 2856
          },
          "GPU-3c2fb581-708a-5fef-3eaa-5c3cc21a028e": {
            "processes": 3,
            "used_mib": 3910
          }
        },
        "raw": {
          "GPU-3a113474-dd92-6d52-d05b-491e7b020ded": [
            {
              "pid": "3763514",
              "used_mib": 1090
            },
            {
              "pid": "3779038",
              "used_mib": 1766
            }
          ],
          "GPU-3c2fb581-708a-5fef-3eaa-5c3cc21a028e": [
            {
              "pid": "3641391",
              "used_mib": 1054
            },
            {
              "pid": "3649478",
              "used_mib": 1090
            },
            {
              "pid": "3779039",
              "used_mib": 1766
            }
          ]
        },
        "total_used_mib": 6766
      }
    },
    {
      "event": "round_4_wake",
      "gpu": {
        "gpus": {
          "GPU-3a113474-dd92-6d52-d05b-491e7b020ded": {
            "processes": 2,
            "used_mib": 38184
          },
          "GPU-3c2fb581-708a-5fef-3eaa-5c3cc21a028e": {
            "processes": 3,
            "used_mib": 39238
          }
        },
        "raw": {
          "GPU-3a113474-dd92-6d52-d05b-491e7b020ded": [
            {
              "pid": "3763514",
              "used_mib": 1090
            },
            {
              "pid": "3779038",
              "used_mib": 37094
            }
          ],
          "GPU-3c2fb581-708a-5fef-3eaa-5c3cc21a028e": [
            {
              "pid": "3641391",
              "used_mib": 1054
            },
            {
              "pid": "3649478",
              "used_mib": 1090
            },
            {
              "pid": "3779039",
              "used_mib": 37094
            }
          ]
        },
        "total_used_mib": 77422
      }
    },
    {
      "event": "round_4_sleep",
      "gpu": {
        "gpus": {
          "GPU-3a113474-dd92-6d52-d05b-491e7b020ded": {
            "processes": 2,
            "used_mib": 2856
          },
          "GPU-3c2fb581-708a-5fef-3eaa-5c3cc21a028e": {
            "processes": 3,
            "used_mib": 3910
          }
        },
        "raw": {
          "GPU-3a113474-dd92-6d52-d05b-491e7b020ded": [
            {
              "pid": "3763514",
              "used_mib": 1090
            },
            {
              "pid": "3779038",
              "used_mib": 1766
            }
          ],
          "GPU-3c2fb581-708a-5fef-3eaa-5c3cc21a028e": [
            {
              "pid": "3641391",
              "used_mib": 1054
            },
            {
              "pid": "3649478",
              "used_mib": 1090
            },
            {
              "pid": "3779039",
              "used_mib": 1766
            }
          ]
        },
        "total_used_mib": 6766
      }
    },
    {
      "event": "round_5_wake",
      "gpu": {
        "gpus": {
          "GPU-3a113474-dd92-6d52-d05b-491e7b020ded": {
            "processes": 2,
            "used_mib": 38184
          },
          "GPU-3c2fb581-708a-5fef-3eaa-5c3cc21a028e": {
            "processes": 3,
            "used_mib": 39238
          }
        },
        "raw": {
          "GPU-3a113474-dd92-6d52-d05b-491e7b020ded": [
            {
              "pid": "3763514",
              "used_mib": 1090
            },
            {
              "pid": "3779038",
              "used_mib": 37094
            }
          ],
          "GPU-3c2fb581-708a-5fef-3eaa-5c3cc21a028e": [
            {
              "pid": "3641391",
              "used_mib": 1054
            },
            {
              "pid": "3649478",
              "used_mib": 1090
            },
            {
              "pid": "3779039",
              "used_mib": 37094
            }
          ]
        },
        "total_used_mib": 77422
      }
    },
    {
      "event": "round_5_sleep",
      "gpu": {
        "gpus": {
          "GPU-3a113474-dd92-6d52-d05b-491e7b020ded": {
            "processes": 2,
            "used_mib": 2856
          },
          "GPU-3c2fb581-708a-5fef-3eaa-5c3cc21a028e": {
            "processes": 3,
            "used_mib": 3910
          }
        },
        "raw": {
          "GPU-3a113474-dd92-6d52-d05b-491e7b020ded": [
            {
              "pid": "3763514",
              "used_mib": 1090
            },
            {
              "pid": "3779038",
              "used_mib": 1766
            }
          ],
          "GPU-3c2fb581-708a-5fef-3eaa-5c3cc21a028e": [
            {
              "pid": "3641391",
              "used_mib": 1054
            },
            {
              "pid": "3649478",
              "used_mib": 1090
            },
            {
              "pid": "3779039",
              "used_mib": 1766
            }
          ]
        },
        "total_used_mib": 6766
      }
    },
    {
      "event": "round_6_wake",
      "gpu": {
        "gpus": {
          "GPU-3a113474-dd92-6d52-d05b-491e7b020ded": {
            "processes": 2,
            "used_mib": 38184
          },
          "GPU-3c2fb581-708a-5fef-3eaa-5c3cc21a028e": {
            "processes": 3,
            "used_mib": 39238
          }
        },
        "raw": {
          "GPU-3a113474-dd92-6d52-d05b-491e7b020ded": [
            {
              "pid": "3763514",
              "used_mib": 1090
            },
            {
              "pid": "3779038",
              "used_mib": 37094
            }
          ],
          "GPU-3c2fb581-708a-5fef-3eaa-5c3cc21a028e": [
            {
              "pid": "3641391",
              "used_mib": 1054
            },
            {
              "pid": "3649478",
              "used_mib": 1090
            },
            {
              "pid": "3779039",
              "used_mib": 37094
            }
          ]
        },
        "total_used_mib": 77422
      }
    },
    {
      "event": "round_6_sleep",
      "gpu": {
        "gpus": {
          "GPU-3a113474-dd92-6d52-d05b-491e7b020ded": {
            "processes": 2,
            "used_mib": 2856
          },
          "GPU-3c2fb581-708a-5fef-3eaa-5c3cc21a028e": {
            "processes": 3,
            "used_mib": 3910
          }
        },
        "raw": {
          "GPU-3a113474-dd92-6d52-d05b-491e7b020ded": [
            {
              "pid": "3763514",
              "used_mib": 1090
            },
            {
              "pid": "3779038",
              "used_mib": 1766
            }
          ],
          "GPU-3c2fb581-708a-5fef-3eaa-5c3cc21a028e": [
            {
              "pid": "3641391",
              "used_mib": 1054
            },
            {
              "pid": "3649478",
              "used_mib": 1090
            },
            {
              "pid": "3779039",
              "used_mib": 1766
            }
          ]
        },
        "total_used_mib": 6766
      }
    },
    {
      "event": "round_7_wake",
      "gpu": {
        "gpus": {
          "GPU-3a113474-dd92-6d52-d05b-491e7b020ded": {
            "processes": 2,
            "used_mib": 38184
          },
          "GPU-3c2fb581-708a-5fef-3eaa-5c3cc21a028e": {
            "processes": 3,
            "used_mib": 39238
          }
        },
        "raw": {
          "GPU-3a113474-dd92-6d52-d05b-491e7b020ded": [
            {
              "pid": "3763514",
              "used_mib": 1090
            },
            {
              "pid": "3779038",
              "used_mib": 37094
            }
          ],
          "GPU-3c2fb581-708a-5fef-3eaa-5c3cc21a028e": [
            {
              "pid": "3641391",
              "used_mib": 1054
            },
            {
              "pid": "3649478",
              "used_mib": 1090
            },
            {
              "pid": "3779039",
              "used_mib": 37094
            }
          ]
        },
        "total_used_mib": 77422
      }
    },
    {
      "event": "round_7_sleep",
      "gpu": {
        "gpus": {
          "GPU-3a113474-dd92-6d52-d05b-491e7b020ded": {
            "processes": 2,
            "used_mib": 2856
          },
          "GPU-3c2fb581-708a-5fef-3eaa-5c3cc21a028e": {
            "processes": 3,
            "used_mib": 3910
          }
        },
        "raw": {
          "GPU-3a113474-dd92-6d52-d05b-491e7b020ded": [
            {
              "pid": "3763514",
              "used_mib": 1090
            },
            {
              "pid": "3779038",
              "used_mib": 1766
            }
          ],
          "GPU-3c2fb581-708a-5fef-3eaa-5c3cc21a028e": [
            {
              "pid": "3641391",
              "used_mib": 1054
            },
            {
              "pid": "3649478",
              "used_mib": 1090
            },
            {
              "pid": "3779039",
              "used_mib": 1766
            }
          ]
        },
        "total_used_mib": 6766
      }
    },
    {
      "event": "round_8_wake",
      "gpu": {
        "gpus": {
          "GPU-3a113474-dd92-6d52-d05b-491e7b020ded": {
            "processes": 2,
            "used_mib": 38184
          },
          "GPU-3c2fb581-708a-5fef-3eaa-5c3cc21a028e": {
            "processes": 3,
            "used_mib": 39238
          }
        },
        "raw": {
          "GPU-3a113474-dd92-6d52-d05b-491e7b020ded": [
            {
              "pid": "3763514",
              "used_mib": 1090
            },
            {
              "pid": "3779038",
              "used_mib": 37094
            }
          ],
          "GPU-3c2fb581-708a-5fef-3eaa-5c3cc21a028e": [
            {
              "pid": "3641391",
              "used_mib": 1054
            },
            {
              "pid": "3649478",
              "used_mib": 1090
            },
            {
              "pid": "3779039",
              "used_mib": 37094
            }
          ]
        },
        "total_used_mib": 77422
      }
    },
    {
      "event": "round_8_sleep",
      "gpu": {
        "gpus": {
          "GPU-3a113474-dd92-6d52-d05b-491e7b020ded": {
            "processes": 2,
            "used_mib": 2856
          },
          "GPU-3c2fb581-708a-5fef-3eaa-5c3cc21a028e": {
            "processes": 3,
            "used_mib": 3910
          }
        },
        "raw": {
          "GPU-3a113474-dd92-6d52-d05b-491e7b020ded": [
            {
              "pid": "3763514",
              "used_mib": 1090
            },
            {
              "pid": "3779038",
              "used_mib": 1766
            }
          ],
          "GPU-3c2fb581-708a-5fef-3eaa-5c3cc21a028e": [
            {
              "pid": "3641391",
              "used_mib": 1054
            },
            {
              "pid": "3649478",
              "used_mib": 1090
            },
            {
              "pid": "3779039",
              "used_mib": 1766
            }
          ]
        },
        "total_used_mib": 6766
      }
    },
    {
      "event": "round_9_wake",
      "gpu": {
        "gpus": {
          "GPU-3a113474-dd92-6d52-d05b-491e7b020ded": {
            "processes": 2,
            "used_mib": 38184
          },
          "GPU-3c2fb581-708a-5fef-3eaa-5c3cc21a028e": {
            "processes": 3,
            "used_mib": 39238
          }
        },
        "raw": {
          "GPU-3a113474-dd92-6d52-d05b-491e7b020ded": [
            {
              "pid": "3763514",
              "used_mib": 1090
            },
            {
              "pid": "3779038",
              "used_mib": 37094
            }
          ],
          "GPU-3c2fb581-708a-5fef-3eaa-5c3cc21a028e": [
            {
              "pid": "3641391",
              "used_mib": 1054
            },
            {
              "pid": "3649478",
              "used_mib": 1090
            },
            {
              "pid": "3779039",
              "used_mib": 37094
            }
          ]
        },
        "total_used_mib": 77422
      }
    },
    {
      "event": "round_9_sleep",
      "gpu": {
        "gpus": {
          "GPU-3a113474-dd92-6d52-d05b-491e7b020ded": {
            "processes": 2,
            "used_mib": 2856
          },
          "GPU-3c2fb581-708a-5fef-3eaa-5c3cc21a028e": {
            "processes": 3,
            "used_mib": 3910
          }
        },
        "raw": {
          "GPU-3a113474-dd92-6d52-d05b-491e7b020ded": [
            {
              "pid": "3763514",
              "used_mib": 1090
            },
            {
              "pid": "3779038",
              "used_mib": 1766
            }
          ],
          "GPU-3c2fb581-708a-5fef-3eaa-5c3cc21a028e": [
            {
              "pid": "3641391",
              "used_mib": 1054
            },
            {
              "pid": "3649478",
              "used_mib": 1090
            },
            {
              "pid": "3779039",
              "used_mib": 1766
            }
          ]
        },
        "total_used_mib": 6766
      }
    }
  ],
  "sleep_level": 1,
  "sleep_used_mib_p95": 6766.0
}
